kraken_etl/__init__.py
kraken_etl/flask_routes.py
kraken_etl/kraken_etl.py
kraken_etl/kraken_etls.py
kraken_etl/helpers/__init__.py
kraken_etl/helpers/etl_api.py
kraken_etl/helpers/etl_extract.py
kraken_etl/helpers/etl_io.py
kraken_etl/helpers/etl_load.py
kraken_etl/helpers/etl_pipeline.py
kraken_etl/helpers/etl_transform.py
kraken_etl/helpers/json.py
kraken_etl-0.0.3.dist-info/LICENSE.txt
kraken_etl-0.0.3.dist-info/METADATA
kraken_etl-0.0.3.dist-info/WHEEL
kraken_etl-0.0.3.dist-info/top_level.txt
kraken_etl-0.0.3.dist-info/RECORD
